laia_cli/__init__.py
laia_cli/cli.py
laia_cli/commands/__init__.py
laia_cli/commands/generate_schema.py
laia_cli/commands/init_project.py
laia_cli/commands/run_laia_flutter.py
laia_cli/commands/start_project.py
laia_cli/generators/__init__.py
laia_cli/generators/files_generator.py
laia_cli/generators/generate_service_ts.py
laia_cli/generators/generate_ts_interface.py
laia_cli/generators/kebab_case_converter.py
laia_cli/generators/backoffice/__init__.py
laia_cli/generators/backoffice/backoffice_generator.py
laia_cli/generators/backoffice/angular/__init__.py
laia_cli/generators/backoffice/angular/angular_generator.py
laia_cli/generators/backoffice/angular/kebab_pipe_creator.py
laia_cli/generators/backoffice/angular/route_to_app_routing.py
laia_cli/generators/backoffice/angular/app_component/__init__.py
laia_cli/generators/backoffice/angular/app_component/app_component_html.py
laia_cli/generators/backoffice/angular/app_component/app_component_module.py
laia_cli/generators/backoffice/angular/app_component/app_component_scss.py
laia_cli/generators/backoffice/angular/app_component/app_component_ts.py
laia_cli/generators/backoffice/angular/app_component/global_page_style.py
laia_cli/generators/backoffice/angular/auth/__init__.py
laia_cli/generators/backoffice/angular/auth/auth_component_html.py
laia_cli/generators/backoffice/angular/auth/auth_component_scss.py
laia_cli/generators/backoffice/angular/auth/auth_component_ts.py
laia_cli/generators/backoffice/angular/auth/new_user_html.py
laia_cli/generators/backoffice/angular/auth/new_user_scss.py
laia_cli/generators/backoffice/angular/auth/new_user_ts.py
laia_cli/generators/backoffice/angular/home/__init__.py
laia_cli/generators/backoffice/angular/home/home_component_html.py
laia_cli/generators/backoffice/angular/home/home_component_scss.py
laia_cli/generators/backoffice/angular/home/home_component_ts.py
laia_cli/generators/backoffice/angular/login/__init__.py
laia_cli-0.1.13.dist-info/licenses/LICENSE
laia_cli-0.1.13.dist-info/METADATA
laia_cli-0.1.13.dist-info/WHEEL
laia_cli-0.1.13.dist-info/entry_points.txt
laia_cli-0.1.13.dist-info/top_level.txt
laia_cli-0.1.13.dist-info/RECORD
