Metadata-Version: 2.4
Name: laia-cli
Version: 0.1.13
Summary: CLI de la librería de LAIA
Author: Itziar
Author-email: itziar.mensa08@gmail.com
Classifier: Programming Language :: Python :: 3
Classifier: License :: OSI Approved :: MIT License
Classifier: Operating System :: OS Independent
Requires-Python: >=3.9
License-File: LICENSE
Requires-Dist: pydantic>=2.0
Requires-Dist: fastapi>=0.100.0
Requires-Dist: pymongo>=4.0
Requires-Dist: bcrypt>=4.0
Requires-Dist: nest_asyncio>=1.5
Requires-Dist: python-dotenv>=1.0
Requires-Dist: uvicorn>=0.22
Requires-Dist: rdflib>=7.0
Dynamic: author
Dynamic: author-email
Dynamic: classifier
Dynamic: license-file
Dynamic: requires-dist
Dynamic: requires-python
Dynamic: summary
